LICENSE
MANIFEST.in
README.md
pavement.py
setup.py
ipygrader/ipygrader.py
ipygrader.egg-info/PKG-INFO
ipygrader.egg-info/SOURCES.txt
ipygrader.egg-info/dependency_links.txt
ipygrader.egg-info/not-zip-safe
ipygrader.egg-info/top_level.txt