Metadata-Version: 1.1
Name: ipygrader
Version: 0.0.0
Summary: Jupyter notebooks gradding using VPL and Moodle
Home-page: http://github.com/jdvelasq/ipygrader
Author: Juan D. Velasquez
Author-email: jdvelasq@unal.edu.co
License: MIT
Keywords: Jupyter Moodle Gradding
Platform: UNKNOWN
Classifier: Development Status :: 3 - Alpha
Classifier: License :: OSI Approved :: MIT License
Classifier: Programming Language :: Python :: 3.5
Classifier: Intended Audience :: Education
Classifier: License :: Free For Educational Use
Classifier: Topic :: Education :: Testing
Classifier: Framework :: Jupyter
